gustaf/__init__.py
gustaf/_base.py
gustaf/_version.py
gustaf/edges.py
gustaf/faces.py
gustaf/settings.py
gustaf/show.py
gustaf/vertices.py
gustaf/volumes.py
gustaf/create/__init__.py
gustaf/create/edges.py
gustaf/create/faces.py
gustaf/create/vertices.py
gustaf/create/volumes.py
gustaf/helpers/__init__.py
gustaf/helpers/_base.py
gustaf/helpers/data.py
gustaf/helpers/notebook.py
gustaf/helpers/options.py
gustaf/helpers/raise_if.py
gustaf/io/__init__.py
gustaf/io/default.py
gustaf/io/ioutils.py
gustaf/io/meshio.py
gustaf/io/mfem.py
gustaf/io/mixd.py
gustaf/io/nutils.py
gustaf/utils/__init__.py
gustaf/utils/arr.py
gustaf/utils/connec.py
gustaf/utils/log.py
gustaf/utils/tictoc.py
gustaf-0.1.2.dist-info/licenses/LICENSE.txt
gustaf-0.1.2.dist-info/METADATA
gustaf-0.1.2.dist-info/WHEEL
gustaf-0.1.2.dist-info/top_level.txt
gustaf-0.1.2.dist-info/RECORD
