Metadata-Version: 2.4
Name: gustaf
Version: 0.1.2
Summary: Process and visualize numerical-analysis-geometries.
Author-email: Jaewook Lee <jaewooklee042@gmail.com>
License: MIT License
Keywords: numerical-analysis,geometry,visualization,mesh
Classifier: Development Status :: 4 - Beta
Classifier: License :: OSI Approved :: MIT License
Classifier: Programming Language :: Python
Classifier: Programming Language :: Python :: 3.9
Classifier: Programming Language :: Python :: 3.10
Classifier: Programming Language :: Python :: 3.11
Classifier: Programming Language :: Python :: 3.12
Classifier: Programming Language :: Python :: 3.13
Classifier: Natural Language :: English
Classifier: Topic :: Scientific/Engineering
Requires-Python: >=3.9
License-File: LICENSE.txt
Requires-Dist: numpy
Requires-Dist: packaging
Provides-Extra: all
Requires-Dist: vedo>=2023.5.0; extra == "all"
Requires-Dist: scipy; extra == "all"
Requires-Dist: meshio; extra == "all"
Requires-Dist: napf>=0.0.5; extra == "all"
Requires-Dist: funi>=0.0.1; extra == "all"
Requires-Dist: requests; extra == "all"
Requires-Dist: ipywidgets; extra == "all"
Requires-Dist: k3d; extra == "all"
Provides-Extra: test
Requires-Dist: pytest; extra == "test"
Requires-Dist: funi>=0.0.1; extra == "test"
Requires-Dist: napf>=0.0.5; extra == "test"
Provides-Extra: dev
Requires-Dist: pre-commit; extra == "dev"
Requires-Dist: vedo>=2023.5.0; extra == "dev"
Requires-Dist: scipy; extra == "dev"
Requires-Dist: meshio; extra == "dev"
Requires-Dist: napf>=0.0.5; extra == "dev"
Requires-Dist: funi>=0.0.1; extra == "dev"
Requires-Dist: requests; extra == "dev"
Requires-Dist: ipywidgets; extra == "dev"
Requires-Dist: k3d; extra == "dev"
Requires-Dist: pytest; extra == "dev"
Dynamic: license-file
